toplib/__init__.py
toplib/models.py
toplib/topcli.py
topsispack_NG-0.1.1.dist-info/METADATA
topsispack_NG-0.1.1.dist-info/WHEEL
topsispack_NG-0.1.1.dist-info/entry_points.txt
topsispack_NG-0.1.1.dist-info/top_level.txt
topsispack_NG-0.1.1.dist-info/RECORD
