Metadata-Version: 2.1
Name: topsispack-NG
Version: 0.1.1
Summary: Multiple Criteria Decision Making(MCDM) using TOPSIS
Home-page: https://github.com/CachingNik/TopsisPack
Author: Nikhil Gupta
Author-email: ngupta_be17@thapar.edu
License: UNKNOWN
Keywords: CLI,TOPSIS,Data
Platform: UNKNOWN
Requires-Python: >=2.7
